spd_metrics_id/__init__.py
spd_metrics_id/cli.py
spd_metrics_id/distance.py
spd_metrics_id/id_rate.py
spd_metrics_id/io.py
spd_metrics_id-0.1.1.dist-info/METADATA
spd_metrics_id-0.1.1.dist-info/WHEEL
spd_metrics_id-0.1.1.dist-info/entry_points.txt
spd_metrics_id-0.1.1.dist-info/top_level.txt
spd_metrics_id-0.1.1.dist-info/RECORD
