Metadata-Version: 2.4
Name: spd-metrics-id
Version: 0.1.1
Summary: Compute identification rates for SPD-matrix metrics across resolutions and tasks
Author-email: Kaosar Uddin <mzu0014@auburn.edu>
Requires-Python: >=3.8
Requires-Dist: numpy>=1.20
Requires-Dist: scipy>=1.7
Requires-Dist: matplotlib>=3.0
Requires-Dist: pandas>=1.0
Requires-Dist: seaborn>=0.11
